<?xml version="1.0" encoding="UTF-8"?>
<objects serializationModel="Studio.02.02.00">
	<object class="AudioFile" id="{8a5acfba-04f9-4de5-a0eb-2a652c14c2d1}">
		<property name="assetPath">
			<value>Music/MainMenù/M02_MainTheme_DesolateVersion.wav</value>
		</property>
		<property name="isStreaming">
			<value>true</value>
		</property>
		<property name="frequencyInKHz">
			<value>48</value>
		</property>
		<property name="channelCount">
			<value>2</value>
		</property>
		<property name="length">
			<value>152.13620833333334</value>
		</property>
		<relationship name="masterAssetFolder">
			<destination>{1f5d9776-bd62-46e8-9177-8206a9dfa926}</destination>
		</relationship>
	</object>
</objects>
